README.md
setup.py
rxpy_backpressure/__init__.py
rxpy_backpressure/backpressure.py
rxpy_backpressure/drop.py
rxpy_backpressure/function_runner.py
rxpy_backpressure/latest.py
rxpy_backpressure/locks.py
rxpy_backpressure/observer.py
rxpy_backpressure.egg-info/PKG-INFO
rxpy_backpressure.egg-info/SOURCES.txt
rxpy_backpressure.egg-info/dependency_links.txt
rxpy_backpressure.egg-info/top_level.txt
tests/__init__.py
tests/test_buffer_backpressure_strategy.py
tests/test_drop_backpressure_strategy.py
tests/test_latest_backpressure_strategy.py
tests/mocks/__init__.py
tests/mocks/mock_observer.py