Metadata-Version: 1.1
Name: rxpy-backpressure
Version: 1.0.0
Summary: Simple add ons to be used with RXPY to support back pressure
Home-page: UNKNOWN
Author: Mark Haynes
Author-email: markhaynes.work@gmail.com
License: MIT
Download-URL: https://github.com/daliclass/rxpy-backpressure
Platform: UNKNOWN
